{
  "engine": "TRILLIONX_INTERNET_VECTOR_MEMORY_BLOCK",
  "ts": "2026-05-24T18:27:20.646Z",
  "seal": "e1e938923235400c9b207a2a775294733b326e65de187f2b1798f96d3a9cf5e6",
  "file": "data/trillionx_internet_vector_memory_1779647239588.json",
  "latest": "data/trillionx_internet_vector_memory_latest.json",
  "summary": {
    "files": 4162,
    "routes": 41029,
    "apis": 130446,
    "ws_events": 808,
    "modules": 5945,
    "scripts": 136,
    "errors": 0,
    "ports_in_code": [
      49,
      53,
      68,
      127,
      143,
      164,
      313,
      443,
      1800,
      2000,
      2222,
      2272,
      3000,
      3010,
      3011,
      3012,
      3013,
      3014,
      3015,
      3016,
      3017,
      3018,
      3019,
      3020,
      3021,
      3022,
      3023,
      3024,
      3025,
      3026,
      3027,
      3028,
      3029,
      3033,
      3044,
      3055,
      3099,
      3100,
      3110,
      3111,
      3112,
      3113,
      3114,
      3115,
      3116,
      3117,
      3118,
      3119,
      3150,
      3160,
      3199,
      3333,
      3814,
      4000,
      4444,
      5000,
      8000,
      8008,
      8080,
      8888,
      9000,
      9229,
      9999,
      12563,
      13005,
      13333,
      14433,
      16634,
      16635,
      36589,
      37885,
      40269
    ],
    "open_ports": [
      2000,
      3000,
      12563,
      13005,
      16634,
      16635
    ],
    "codecs": {
      "eth": 2411,
      "json": 1465,
      "sha256": 1106,
      "aes": 1092,
      "http": 967,
      "https": 587,
      "tcp": 551,
      "udp": 532,
      "blockchain": 529,
      "zlib": 527,
      "stratum": 479,
      "btc": 461,
      "wasm": 401,
      "iot": 391,
      "gzip": 341,
      "utxo": 319,
      "websocket": 315,
      "satellite": 312,
      "jsonl": 287,
      "html": 254,
      "brotli": 238,
      "rsa": 236,
      "csv": 194,
      "sha3": 185,
      "blake": 179,
      "merkle": 140,
      "base64": 133,
      "xml": 124,
      "protobuf": 124,
      "msgpack": 124,
      "mqtt": 107,
      "coap": 107,
      "lorawan": 107,
      "grpc": 65,
      "ecdsa": 7,
      "opcua": 6
    },
    "networks": {
      "port": 3815,
      "ip": 3097,
      "route": 2517,
      "net": 2431,
      "latency": 2341,
      "127.0.0.1": 796,
      "ping": 795,
      "socket": 694,
      "dns": 639,
      "interface": 631,
      "ipv4": 536,
      "0.0.0.0": 527,
      "ipv6": 452,
      "eth0": 424,
      "docker0": 373,
      "throughput": 324,
      "localhost": 307,
      "bandwidth": 184,
      "gateway": 129
    },
    "registries": {
      "trillionx": 3841,
      "health": 3138,
      "vr": 3116,
      "memory": 3026,
      "runtime": 2997,
      "mirror": 2830,
      "cache": 2588,
      "module": 2520,
      "raid60": 1937,
      "worker": 990,
      "benchmark": 917,
      "vector": 807,
      "registry": 778,
      "catalog": 622,
      "trillions": 574,
      "plugin": 273
    }
  },
  "health": 100,
  "verdict": "TRILLIONX_VECTOR_INTERNET_BLOCK_READY_SAFE_LOCAL_DECLARED_TARGETS",
  "truth_policy": {
    "safe_only": true,
    "no_global_takeover": true,
    "no_intrusion": true,
    "no_bruteforce": true,
    "declared_targets_only": true,
    "local_repo_index": true,
    "vector_memory": true,
    "internet_support": "only public/declared URLs and local exposed endpoints"
  }
}